Py2Malware/__init__.py
Py2Malware/Py2Malware.py
py2malware-0.1.dist-info/LICENSE.txt
py2malware-0.1.dist-info/METADATA
py2malware-0.1.dist-info/WHEEL
py2malware-0.1.dist-info/RECORD
